pytest_iso-0.4.2.dist-info/METADATA
pytest_iso-0.4.2.dist-info/WHEEL
pytest_iso-0.4.2.dist-info/entry_points.txt
pytest_iso-0.4.2.dist-info/licenses/LICENSE
pytest_iso/__init__.py
pytest_iso/fonts/OFL.txt
pytest_iso/fonts/Roboto-Black.ttf
pytest_iso/fonts/Roboto-BlackItalic.ttf
pytest_iso/fonts/Roboto-Bold.ttf
pytest_iso/fonts/Roboto-BoldItalic.ttf
pytest_iso/fonts/Roboto-ExtraBold.ttf
pytest_iso/fonts/Roboto-ExtraBoldItalic.ttf
pytest_iso/fonts/Roboto-ExtraLight.ttf
pytest_iso/fonts/Roboto-ExtraLightItalic.ttf
pytest_iso/fonts/Roboto-Italic.ttf
pytest_iso/fonts/Roboto-Light.ttf
pytest_iso/fonts/Roboto-LightItalic.ttf
pytest_iso/fonts/Roboto-Medium.ttf
pytest_iso/fonts/Roboto-MediumItalic.ttf
pytest_iso/fonts/Roboto-Regular.ttf
pytest_iso/fonts/Roboto-SemiBold.ttf
pytest_iso/fonts/Roboto-SemiBoldItalic.ttf
pytest_iso/fonts/Roboto-Thin.ttf
pytest_iso/fonts/Roboto-ThinItalic.ttf
pytest_iso/plugin.py
pytest_iso/pytest_iso.abi3.so
pytest_iso-0.4.2.dist-info/RECORD
