Metadata-Version: 2.4
Name: pytest-iso
Version: 0.4.2
Classifier: Development Status :: 4 - Beta
Classifier: Programming Language :: Python
Classifier: Programming Language :: Python :: 3
Classifier: Programming Language :: Python :: 3.9
Classifier: Programming Language :: Python :: 3.10
Classifier: Programming Language :: Python :: 3.11
Classifier: Programming Language :: Python :: 3.12
Classifier: Programming Language :: Python :: 3.13
Classifier: Programming Language :: Python :: 3.14
Classifier: Programming Language :: Rust
Classifier: Programming Language :: Python :: Implementation :: CPython
Classifier: Programming Language :: Python :: Implementation :: PyPy
Classifier: Framework :: Pytest
Classifier: Topic :: Software Development :: Testing
Classifier: Topic :: Software Development :: Quality Assurance
Classifier: Topic :: Documentation
Classifier: License :: OSI Approved :: MIT License
Requires-Dist: pytest>=7.4.0,<9.0.0
License-File: LICENSE
Summary: Plugin for pytest to produce test documentation for code audits.
Author: Sebastian Dirndorfer <pytest.iso@web.de>
Author-email: Sebastian Dirndorfer <pytest.iso@web.de>
License: MIT
Requires-Python: >=3.9
Project-URL: Homepage, https://gitlab.com/sdirndorfer_pr/pytest-iso
Project-URL: Source, https://gitlab.com/sdirndorfer_pr/pytest-iso
Project-URL: Issues, https://gitlab.com/sdirndorfer_pr/pytest-iso/-/issues
